sheetfusion/__init__.py
sheetfusion/__main__.py
sheetfusion/_version.py
sheetfusion/main.py
sheetfusion/args/__init__.py
sheetfusion/args/parser.py
sheetfusion/assets/ascii_logo.txt
sheetfusion/utils/__init__.py
sheetfusion/utils/progress.py
sheetfusion-1.0.6.dist-info/LICENSE
sheetfusion-1.0.6.dist-info/METADATA
sheetfusion-1.0.6.dist-info/WHEEL
sheetfusion-1.0.6.dist-info/entry_points.txt
sheetfusion-1.0.6.dist-info/top_level.txt
sheetfusion-1.0.6.dist-info/RECORD
