Metadata-Version: 2.1
Name: sheetfusion
Version: 1.0.6
Author-email: Mohammad Znz <s.mohammad.znz@gmail.com>
Project-URL: Homepage, https://github.com/SMZ70/SheetFusion
Project-URL: Bug Tracker, https://github.com/SMZ70/SheetFusion/issues
Classifier: Programming Language :: Python :: 3
Classifier: License :: OSI Approved :: MIT License
Classifier: Operating System :: OS Independent
Requires-Python: >=3.9
License-File: LICENSE
Requires-Dist: PyPDF3 ~=1.0.6
Requires-Dist: rich ~=13.7.0
Requires-Dist: setuptools ~=69.0.2
